dedl_stack_client/__init__.py
dedl_stack_client/authn.py
dedl_stack_client/dask.py
dedl_stack_client-2025.5.1.dist-info/LICENSE
dedl_stack_client-2025.5.1.dist-info/METADATA
dedl_stack_client-2025.5.1.dist-info/WHEEL
dedl_stack_client-2025.5.1.dist-info/RECORD
