Metadata-Version: 2.3
Name: dedl-stack-client
Version: 2025.5.1
Summary: Python client for DEDL Stack services
License: Apache-2.0
Author: Christoph Reimer
Author-email: christoph.reimer@eodc.eu
Requires-Python: >=3.11,<4.0
Classifier: License :: OSI Approved :: Apache Software License
Classifier: Programming Language :: Python :: 3
Classifier: Programming Language :: Python :: 3.11
Classifier: Programming Language :: Python :: 3.12
Classifier: Programming Language :: Python :: 3.13
Requires-Dist: cloudpickle (==2.2.1)
Requires-Dist: dask (==2023.8.0)
Requires-Dist: dask-gateway (==2023.1.1)
Requires-Dist: distributed (==2023.8.0)
Requires-Dist: ipykernel (>=6.26.0)
Requires-Dist: lz4 (==4.3.2)
Requires-Dist: msgpack (==1.0.5)
Requires-Dist: pyjwt[crypto] (>=2.8.0)
Requires-Dist: requests (>=2.31.0)
Requires-Dist: rich[jupyter] (>=13.6.0)
Requires-Dist: toolz (==0.12.0)
Requires-Dist: tornado (==6.3.2)
